scanner/__init__.py
scanner/lexycal/__init__.py
scanner/lexycal/lexycal_2.py
scanner/lexycal/lexycal_3.py
scanner/lexycal/lexycal_scanner_PTBR_2.py
scanner/lexycal/lexycal_scanner_PTBR_3.py
scanner/lexycal/token.py
scanner/lexycal/token_type.py
take_blip_scanner-0.0.14.dist-info/LICENSE
take_blip_scanner-0.0.14.dist-info/METADATA
take_blip_scanner-0.0.14.dist-info/WHEEL
take_blip_scanner-0.0.14.dist-info/top_level.txt
take_blip_scanner-0.0.14.dist-info/RECORD
