Metadata-Version: 2.1
Name: take-blip-scanner
Version: 0.0.14
Summary: Take Blip Scanner
Home-page: UNKNOWN
Author: Data & Analytics Research Team
Author-email: analytics.dar@take.net
License: UNKNOWN
Platform: UNKNOWN
Classifier: Programming Language :: Python :: 3
Classifier: License :: OSI Approved :: MIT License
Classifier: Operating System :: OS Independent
Requires-Python: >=3.6
